morestd/__init__.py
morestd/data.py
morestd/file.py
morestd/fs.py
morestd/lsb.py
morestd/net.py
morestd/process.py
morestd/shell.py
morestd/time.py
morestd-0.5.dist-info/METADATA
morestd-0.5.dist-info/RECORD
morestd-0.5.dist-info/WHEEL
morestd-0.5.dist-info/top_level.txt
morestd-0.5.dist-info/zip-safe
