Metadata-Version: 2.1
Name: morestd
Version: 0.5
Summary: A collection of additional standard libraries for Python.
Home-page: https://github.com/fboender/morestd
Author: Ferry Boender
Author-email: ferry.boender@gmail.com
License: MIT
Platform: UNKNOWN
Classifier: Programming Language :: Python :: 3
Classifier: License :: OSI Approved :: MIT License
Classifier: Operating System :: OS Independent
